wikipediaapi/__init__.py
Wikipedia_API-0.5.8.dist-info/LICENSE
Wikipedia_API-0.5.8.dist-info/METADATA
Wikipedia_API-0.5.8.dist-info/WHEEL
Wikipedia_API-0.5.8.dist-info/top_level.txt
Wikipedia_API-0.5.8.dist-info/RECORD
