Metadata-Version: 2.1
Name: Wikipedia-API
Version: 0.5.8
Summary: Python Wrapper for Wikipedia
Home-page: https://github.com/martin-majlis/Wikipedia-API
Author: Martin Majlis
Author-email: martin@majlis.cz
License: MIT
Download-URL: https://github.com/martin-majlis/Wikipedia-API/archive/master.tar.gz
Keywords: Wikipedia API wrapper
Platform: any
Classifier: Development Status :: 5 - Production/Stable
Classifier: Environment :: Web Environment
Classifier: Intended Audience :: Developers
Classifier: Programming Language :: Python
Classifier: Programming Language :: Python :: 3
Classifier: Programming Language :: Python :: 3.4
Classifier: Programming Language :: Python :: 3.5
Classifier: Programming Language :: Python :: 3.6
Classifier: Programming Language :: Python :: 3.7
Classifier: Programming Language :: Python :: 3.8
Classifier: Programming Language :: Python :: 3.9
Classifier: Programming Language :: Python :: 3.10
Classifier: Programming Language :: Python :: 3.11
Classifier: Programming Language :: Python :: Implementation :: CPython
Classifier: Programming Language :: Python :: Implementation :: PyPy
Classifier: License :: OSI Approved :: MIT License
Classifier: Operating System :: OS Independent
Classifier: Topic :: Communications :: Email
Classifier: Topic :: Software Development :: Libraries :: Python Modules
Provides-Extra: testing
License-File: LICENSE
